nexusraven/__init__.py
nexusraven/client.py
nexusraven-0.9.0.dist-info/METADATA
nexusraven-0.9.0.dist-info/WHEEL
nexusraven-0.9.0.dist-info/top_level.txt
nexusraven-0.9.0.dist-info/RECORD
