Metadata-Version: 2.1
Name: nexusraven
Version: 0.9.0
Summary: This package is for using NexusRaven-V2, an open source function calling model, for function calling using OpenAI semantics.
Home-page: https://github.com/nexusflowai/NexusRavenPython
Author: Nexusflow AI
Author-email: info@nexusflow.ai
License: UNKNOWN
Platform: UNKNOWN
Classifier: Programming Language :: Python :: 3.10
Classifier: License :: OSI Approved :: MIT License
Classifier: Operating System :: OS Independent
Requires-Python: >=3.10
Requires-Dist: openai
Requires-Dist: requests
